o2a/__init__.py
o2a/definitions.py
o2a/o2a.py
o2a/converter/__init__.py
o2a/converter/constants.py
o2a/converter/exceptions.py
o2a/converter/mappers.py
o2a/converter/oozie_converter.py
o2a/converter/parsed_node.py
o2a/converter/parser.py
o2a/converter/relation.py
o2a/converter/task.py
o2a/converter/workflow.py
o2a/mappers/__init__.py
o2a/mappers/action_mapper.py
o2a/mappers/base_mapper.py
o2a/mappers/decision_mapper.py
o2a/mappers/dummy_mapper.py
o2a/mappers/end_mapper.py
o2a/mappers/fs_mapper.py
o2a/mappers/git_mapper.py
o2a/mappers/kill_mapper.py
o2a/mappers/mapreduce_mapper.py
o2a/mappers/null_mapper.py
o2a/mappers/pig_mapper.py
o2a/mappers/prepare_mixin.py
o2a/mappers/shell_mapper.py
o2a/mappers/spark_mapper.py
o2a/mappers/ssh_mapper.py
o2a/mappers/start_mapper.py
o2a/mappers/subworkflow_mapper.py
o2a/o2a_libs/__init__.py
o2a/o2a_libs/el_basic_functions.py
o2a/o2a_libs/el_wf_functions.py
o2a/utils/__init__.py
o2a/utils/constants.py
o2a/utils/el_utils.py
o2a/utils/file_archive_extractors.py
o2a/utils/relation_utils.py
o2a/utils/template_utils.py
o2a/utils/xml_utils.py
tests/__init__.py
tests/test_templates.py
tests/converter/__init__.py
tests/converter/test_oozie_converter.py
tests/converter/test_oozie_parser.py
tests/converter/test_parsed_node.py
tests/mappers/__init__.py
tests/mappers/test_archive_extractor.py
tests/mappers/test_base_mapper.py
tests/mappers/test_decision_mapper.py
tests/mappers/test_dummy_mapper.py
tests/mappers/test_end_mapper.py
tests/mappers/test_file_extractor.py
tests/mappers/test_fs_mapper.py
tests/mappers/test_git_mapper.py
tests/mappers/test_kill_mapper.py
tests/mappers/test_mapreduce_mapper.py
tests/mappers/test_pig_mapper.py
tests/mappers/test_prepare_mixin.py
tests/mappers/test_shell_mapper.py
tests/mappers/test_spark_mapper.py
tests/mappers/test_ssh_mapper.py
tests/mappers/test_start_mapper.py
tests/mappers/test_subworkflow_mapper.py
tests/o2a_libs/__init__.py
tests/o2a_libs/test_el_basic_functions.py
tests/utils/__init__.py
o2a_potiuk-0.0.1.dist-info/LICENSE
o2a_potiuk-0.0.1.dist-info/LICENSE.txt
o2a_potiuk-0.0.1.dist-info/METADATA
o2a_potiuk-0.0.1.dist-info/WHEEL
o2a_potiuk-0.0.1.dist-info/top_level.txt
o2a_potiuk-0.0.1.dist-info/RECORD
