Metadata-Version: 2.1
Name: o2a-potiuk
Version: 0.0.1
Summary: Oozie To Airflow migration tool
Home-page: https://github.com/GoogleCloudPlatform/oozie-to-airflow
Author: Jarek Potiuk, Szymon Przedwojski, Kamil Breguła, Feng Lu, Cameron Moberg
Author-email: jarek.potiuk@polidea.com
License: UNKNOWN
Platform: UNKNOWN
Classifier: Programming Language :: Python :: 3.6
Classifier: Programming Language :: Python :: 3.7
Classifier: Programming Language :: Python :: 3.8
Classifier: License :: OSI Approved :: Apache Software License
Classifier: Operating System :: OS Independent
